Metadata-Version: 1.0
Name: distributions-srg-001
Version: 0.1
Summary: Gaussian and Binomial distributions
Home-page: UNKNOWN
Author: Somya Rajiv Gupta
Author-email: thesomyagupta@gmail.com
License: UNKNOWN
Platform: UNKNOWN
